.DS_Store
__init__.py
api_complete.py
cloud_connect_aws.py
detects.py
device_control_policies.py
event_streams.py
falconx_sandbox.py
firewall_management.py
firewall_policies.py
host_group.py
hosts.py
incidents.py
intel.py
iocs.py
oauth2.py
prevention_policy.py
real_time_response.py
real_time_response_admin.py
sensor_update_policy.py
spotlight_vulnerabilities.py
user_management.py
csfalcon-0.1.1.dist-info/LICENSE
csfalcon-0.1.1.dist-info/METADATA
csfalcon-0.1.1.dist-info/WHEEL
csfalcon-0.1.1.dist-info/top_level.txt
csfalcon-0.1.1.dist-info/RECORD
